langchain_google_firestore/__init__.py
langchain_google_firestore/chat_message_history.py
langchain_google_firestore/common.py
langchain_google_firestore/document_converter.py
langchain_google_firestore/document_loader.py
langchain_google_firestore/py.typed
langchain_google_firestore/vectorstores.py
langchain_google_firestore/version.py
langchain_google_firestore-0.4.0.dist-info/LICENSE
langchain_google_firestore-0.4.0.dist-info/METADATA
langchain_google_firestore-0.4.0.dist-info/WHEEL
langchain_google_firestore-0.4.0.dist-info/top_level.txt
langchain_google_firestore-0.4.0.dist-info/RECORD
