Metadata-Version: 2.1
Name: langchain-google-firestore
Version: 0.4.0
Summary: LangChain integrations for Google Cloud Firestore
Author-email: Google LLC <googleapis-packages@google.com>
License: 
Project-URL: Homepage, https://github.com/googleapis/langchain-google-firestore-python
Project-URL: Repository, https://github.com/googleapis/langchain-google-firestore-python.git
Project-URL: Bug Tracker, https://github.com/googleapis/langchain-google-firestore-python/issues
Project-URL: Changelog, https://github.com/googleapis/langchain-google-firestore-python/blob/main/CHANGELOG.md
Classifier: Intended Audience :: Developers
Classifier: License :: OSI Approved :: Apache Software License
Classifier: Programming Language :: Python
Classifier: Programming Language :: Python :: 3
Classifier: Programming Language :: Python :: 3.8
Classifier: Programming Language :: Python :: 3.9
Classifier: Programming Language :: Python :: 3.10
Classifier: Programming Language :: Python :: 3.11
Classifier: Programming Language :: Python :: 3.12
Requires-Python: >=3.8
License-File: LICENSE
Requires-Dist: langchain-core <1.0.0,>=0.1.1
Requires-Dist: langchain-community <1.0.0,>=0.0.18
Requires-Dist: google-cloud-firestore <3.0.0,>=2.16.0
Requires-Dist: google-cloud-storage <3.0.0,>=2.18.2
Requires-Dist: more-itertools <11.0.0,>=10.2.0
Requires-Dist: requests <2.33.0,>=2.32.3
Provides-Extra: test
Requires-Dist: black[jupyter] ==24.8.0 ; extra == 'test'
Requires-Dist: isort ==5.13.2 ; extra == 'test'
Requires-Dist: mypy ==1.11.2 ; extra == 'test'
Requires-Dist: pytest-asyncio ==0.24.0 ; extra == 'test'
Requires-Dist: pytest ==8.3.3 ; extra == 'test'
Requires-Dist: pytest-cov ==5.0.0 ; extra == 'test'
